ocsh.py
pocsh.py
ocsh-20230922.dist-info/METADATA
ocsh-20230922.dist-info/WHEEL
ocsh-20230922.dist-info/entry_points.txt
ocsh-20230922.dist-info/top_level.txt
ocsh-20230922.dist-info/RECORD
