Metadata-Version: 2.1
Name: ocsh
Version: 20230922
Summary: SSH password log-in and command automator
Author-email: Laurent Ghigonis <ooookiwi@gmail.com>
License: BSD-3-Clause
Project-URL: Homepage, https://github.com/looran/ocsh
Keywords: ssh,bouncer,pass
Requires-Python: >=3.0
Requires-Dist: pexpect
Requires-Dist: importlib-metadata ; python_version < "3.8"
